README.md
setup.cfg
setup.py
PySnappydata.egg-info/PKG-INFO
PySnappydata.egg-info/SOURCES.txt
PySnappydata.egg-info/dependency_links.txt
PySnappydata.egg-info/entry_points.txt
PySnappydata.egg-info/not-zip-safe
PySnappydata.egg-info/requires.txt
PySnappydata.egg-info/top_level.txt
SDTCLIService/LocatorService.py
SDTCLIService/SnappyDataService.py
SDTCLIService/__init__.py
SDTCLIService/constants.py
SDTCLIService/ttypes.py
pysnappydata/__init__.py
pysnappydata/common.py
pysnappydata/exc.py
pysnappydata/snappydata.py
pysnappydata/sqlalchemy_snappydata.py